torchtsmixer/__init__.py
torchtsmixer/layers.py
torchtsmixer/tsmixer.py
torchtsmixer/tsmixer_ext.py
pytorch_tsmixer-0.2.0.dist-info/LICENSE
pytorch_tsmixer-0.2.0.dist-info/METADATA
pytorch_tsmixer-0.2.0.dist-info/WHEEL
pytorch_tsmixer-0.2.0.dist-info/top_level.txt
pytorch_tsmixer-0.2.0.dist-info/RECORD
