Metadata-Version: 2.1
Name: pytorch-tsmixer
Version: 0.2.0
Summary: An pytorch-based reimplementation of TSMixer.
Author: Konstantin Ditschuneit
Project-URL: Homepage, https://github.com/ditschuk/pytorch-tsmixer
Classifier: Programming Language :: Python :: 3
Classifier: License :: OSI Approved :: MIT License
Classifier: Operating System :: OS Independent
Requires-Python: >=3.8
License-File: LICENSE
Requires-Dist: torch >1.6
Provides-Extra: test
Requires-Dist: hypothesis ; extra == 'test'
Requires-Dist: pre-commit ; extra == 'test'
